json_to_python/__init__.py
json_to_python/json_to_python.py
json_to_python-0.3.dist-info/METADATA
json_to_python-0.3.dist-info/WHEEL
json_to_python-0.3.dist-info/top_level.txt
json_to_python-0.3.dist-info/RECORD
