Metadata-Version: 2.1
Name: json-to-python
Version: 0.3
Summary: converts api json responses to python objects
Home-page: https://github.com/arokosaki/json_to_python
Author: kobi kolodner
Author-email: kobi@commugen.com
License: MIT
Classifier: Development Status :: 2 - Pre-Alpha
